installreq.py
installreq-1.0.0.dist-info/WHEEL
installreq-1.0.0.dist-info/METADATA
installreq-1.0.0.dist-info/RECORD
