Metadata-Version: 2.1
Name: installreq
Version: 1.0.0
Summary: Installs all the requirements for a file and runs it
Author-email: Guanciottaman <italia.matteo00@gmail.com>
Requires-Python: >=3.8
Classifier: Development Status :: 3 - Alpha
Classifier: License :: OSI Approved :: GNU General Public License (GPL)
Classifier: Natural Language :: English
Classifier: Operating System :: OS Independent
Classifier: Programming Language :: Python
Classifier: Programming Language :: Python :: 3.8
Classifier: Programming Language :: Python :: 3.9
Classifier: Programming Language :: Python :: 3.10
Classifier: Programming Language :: Python :: 3.11
